dicebag.py
dicebag-0.0.2.dist-info/METADATA
dicebag-0.0.2.dist-info/WHEEL
dicebag-0.0.2.dist-info/top_level.txt
dicebag-0.0.2.dist-info/RECORD
