Metadata-Version: 2.1
Name: dicebag
Version: 0.0.2
Summary: An infinite bag of dice.
Home-page: UNKNOWN
Author: Mark Smith
Author-email: judy@judy.co.uk
License: MIT
Platform: UNKNOWN
Classifier: License :: OSI Approved :: MIT License
Classifier: Programming Language :: Python
Classifier: Programming Language :: Python :: 3
Classifier: Programming Language :: Python :: 3.6
Requires-Python: >=3.6.0
